emmental/__init__.py
emmental/_version.py
emmental/data.py
emmental/emmental-default-config.yaml
emmental/learner.py
emmental/meta.py
emmental/model.py
emmental/scorer.py
emmental/task.py
emmental/contrib/__init__.py
emmental/contrib/slicing/__init__.py
emmental/contrib/slicing/data.py
emmental/contrib/slicing/slicing_function.py
emmental/contrib/slicing/task.py
emmental/contrib/slicing/modules/__init__.py
emmental/contrib/slicing/modules/slice_attention_module.py
emmental/contrib/slicing/modules/utils.py
emmental/logging/__init__.py
emmental/logging/checkpointer.py
emmental/logging/json_writer.py
emmental/logging/log_writer.py
emmental/logging/logging_manager.py
emmental/logging/tensorboard_writer.py
emmental/logging/wandb_writer.py
emmental/metrics/__init__.py
emmental/metrics/accuracy.py
emmental/metrics/accuracy_f1.py
emmental/metrics/fbeta.py
emmental/metrics/matthews_correlation.py
emmental/metrics/mean_squared_error.py
emmental/metrics/pearson_correlation.py
emmental/metrics/pearson_spearman.py
emmental/metrics/precision.py
emmental/metrics/recall.py
emmental/metrics/roc_auc.py
emmental/metrics/spearman_correlation.py
emmental/modules/__init__.py
emmental/modules/embedding_module.py
emmental/modules/identity_module.py
emmental/modules/rnn_module.py
emmental/modules/sparse_linear_module.py
emmental/optimizers/__init__.py
emmental/optimizers/bert_adam.py
emmental/schedulers/__init__.py
emmental/schedulers/mixed_scheduler.py
emmental/schedulers/round_robin_scheduler.py
emmental/schedulers/scheduler.py
emmental/schedulers/sequential_scheduler.py
emmental/utils/__init__.py
emmental/utils/parse_args.py
emmental/utils/seed.py
emmental/utils/utils.py
emmental-0.1.1.dist-info/LICENSE
emmental-0.1.1.dist-info/METADATA
emmental-0.1.1.dist-info/WHEEL
emmental-0.1.1.dist-info/top_level.txt
emmental-0.1.1.dist-info/RECORD
