Metadata-Version: 2.1
Name: emmental
Version: 0.1.1
Summary: A framework for building multi-modal multi-task learning systems.
Home-page: https://github.com/SenWu/emmental
Author: Sen Wu
Author-email: senwu@cs.stanford.edu
License: MIT
Project-URL: Tracker, https://github.com/SenWu/emmental/issues
Project-URL: Source, https://github.com/SenWu/emmental
Keywords: emmental,multi task learning,deep learing
Platform: UNKNOWN
Classifier: Development Status :: 3 - Alpha
Classifier: Intended Audience :: Developers
Classifier: Programming Language :: Python
Classifier: Programming Language :: Python :: 3
Classifier: Programming Language :: Python :: 3.6
Classifier: Programming Language :: Python :: 3.7
Classifier: Programming Language :: Python :: 3.8
Classifier: Programming Language :: Python :: 3.9
Classifier: Programming Language :: Python :: 3 :: Only
Requires-Python: >=3.6
License-File: LICENSE
Requires-Dist: numpy (<2.0,>=1.11)
Requires-Dist: pyyaml (<6.0,>=5.1)
Requires-Dist: scikit-learn (<2.0,>=0.20.0)
Requires-Dist: scipy (<2.0.0,>=1.1.0)
Requires-Dist: tensorboard (<3.0.0,>=1.15.0)
Requires-Dist: torch (<2.0.0,>=1.3.1)
Requires-Dist: tqdm (<5.0.0,>=4.41.0)
Requires-Dist: wandb (<1.0.0,>=0.10.0)
